README.rst
setup.py
pman_reaper/reaper.py
pman_reaper.egg-info/PKG-INFO
pman_reaper.egg-info/SOURCES.txt
pman_reaper.egg-info/dependency_links.txt
pman_reaper.egg-info/not-zip-safe
pman_reaper.egg-info/requires.txt
pman_reaper.egg-info/top_level.txt