Metadata-Version: 1.0
Name: pman-reaper
Version: 0.1
Summary: Reaper for pman jobs
Home-page: UNKNOWN
Author: Parul Singh
Author-email: singh.p@husky.neu.edu
License: MIT
Platform: UNKNOWN
